{
    "version": "3.16.7",
    "flags": {},
    "shapes": [
        {
            "label": "Nail Cutter",
            "line_color": null,
            "fill_color": null,
            "points": [
                [
                    214,
                    129
                ],
                [
                    211,
                    129
                ],
                [
                    210,
                    130
                ],
                [
                    209,
                    130
                ],
                [
                    208,
                    130
                ],
                [
                    207,
                    129
                ],
                [
                    207,
                    128
                ],
                [
                    208,
                    127
                ],
                [
                    210,
                    127
                ],
                [
                    211,
                    129
                ],
                [
                    214,
                    129
                ],
                [
                    214,
                    127
                ],
                [
                    213,
                    126
                ],
                [
                    206,
                    126
                ],
                [
                    185,
                    125
                ],
                [
                    172,
                    125
                ],
                [
                    160,
                    126
                ],
                [
                    155,
                    126
                ],
                [
                    147,
                    128
                ],
                [
                    143,
                    131
                ],
                [
                    140,
                    134
                ],
                [
                    139,
                    136
                ],
                [
                    140,
                    138
                ],
                [
                    141,
                    138
                ],
                [
                    153,
                    139
                ],
                [
                    171,
                    138
                ],
                [
                    198,
                    134
                ],
                [
                    209,
                    132
                ],
                [
                    212,
                    131
                ]
            ],
            "shape_type": "polygon",
            "flags": {}
        }
    ],
    "lineColor": [
        255,
        0,
        127,
        128
    ],
    "fillColor": [
        255,
        0,
        0,
        128
    ],
    "imagePath": "Nailcutter3_B2_L4A_C1_Loc1_phi1_th1_3.jpg",
    "imageHeight": 400,
    "imageWidth": 419
}