{
    "version": "3.16.7",
    "flags": {},
    "shapes": [
        {
            "label": "Gun",
            "line_color": null,
            "fill_color": null,
            "points": [
                [
                    201,
                    206
                ],
                [
                    201,
                    204
                ],
                [
                    201,
                    203
                ],
                [
                    201,
                    202
                ],
                [
                    201,
                    200
                ],
                [
                    202,
                    199
                ],
                [
                    205,
                    198
                ],
                [
                    208,
                    198
                ],
                [
                    214,
                    198
                ],
                [
                    216,
                    198
                ],
                [
                    217,
                    198
                ],
                [
                    218,
                    200
                ],
                [
                    218,
                    202
                ],
                [
                    218,
                    204
                ],
                [
                    218,
                    205
                ],
                [
                    218,
                    206
                ],
                [
                    219,
                    207
                ],
                [
                    220,
                    207
                ],
                [
                    220,
                    207
                ],
                [
                    221,
                    230
                ],
                [
                    220,
                    231
                ],
                [
                    220,
                    232
                ],
                [
                    220,
                    236
                ],
                [
                    220,
                    238
                ],
                [
                    222,
                    239
                ],
                [
                    222,
                    240
                ],
                [
                    223,
                    248
                ],
                [
                    224,
                    257
                ],
                [
                    223,
                    259
                ],
                [
                    220,
                    261
                ],
                [
                    216,
                    262
                ],
                [
                    215,
                    264
                ],
                [
                    213,
                    266
                ],
                [
                    214,
                    268
                ],
                [
                    214,
                    269
                ],
                [
                    213,
                    270
                ],
                [
                    211,
                    271
                ],
                [
                    208,
                    271
                ],
                [
                    206,
                    271
                ],
                [
                    204,
                    271
                ],
                [
                    203,
                    269
                ],
                [
                    203,
                    267
                ],
                [
                    202,
                    265
                ],
                [
                    200,
                    265
                ],
                [
                    197,
                    265
                ],
                [
                    190,
                    267
                ],
                [
                    185,
                    268
                ],
                [
                    179,
                    271
                ],
                [
                    176,
                    271
                ],
                [
                    171,
                    271
                ],
                [
                    163,
                    272
                ],
                [
                    161,
                    271
                ],
                [
                    160,
                    269
                ],
                [
                    159,
                    266
                ],
                [
                    159,
                    264
                ],
                [
                    159,
                    261
                ],
                [
                    159,
                    259
                ],
                [
                    159,
                    257
                ],
                [
                    160,
                    255
                ],
                [
                    176,
                    252
                ],
                [
                    185,
                    250
                ],
                [
                    189,
                    248
                ],
                [
                    190,
                    246
                ],
                [
                    190,
                    243
                ],
                [
                    190,
                    241
                ],
                [
                    190,
                    238
                ],
                [
                    190,
                    237
                ],
                [
                    192,
                    234
                ],
                [
                    194,
                    234
                ],
                [
                    196,
                    234
                ],
                [
                    197,
                    234
                ],
                [
                    197,
                    234
                ],
                [
                    197,
                    235
                ],
                [
                    197,
                    236
                ],
                [
                    196,
                    236
                ],
                [
                    194,
                    236
                ],
                [
                    192,
                    238
                ],
                [
                    192,
                    240
                ],
                [
                    193,
                    242
                ],
                [
                    197,
                    243
                ],
                [
                    200,
                    243
                ],
                [
                    202,
                    242
                ],
                [
                    202,
                    240
                ],
                [
                    202,
                    238
                ],
                [
                    201,
                    237
                ],
                [
                    198,
                    236
                ],
                [
                    197,
                    236
                ],
                [
                    197,
                    234
                ],
                [
                    199,
                    234
                ],
                [
                    202,
                    234
                ],
                [
                    202,
                    233
                ],
                [
                    202,
                    224
                ],
                [
                    203,
                    213
                ],
                [
                    202,
                    208
                ]
            ],
            "shape_type": "polygon",
            "flags": {}
        }
    ],
    "lineColor": [
        255,
        0,
        127,
        128
    ],
    "fillColor": [
        255,
        0,
        0,
        128
    ],
    "imagePath": "gun1_B1_L1_C1_Loc1_phi1_th1_4.jpg",
    "imageHeight": 457,
    "imageWidth": 426,
    "label": "Gun"
}